LICENSE
README.md
setup.py
pywebio_battery/__init__.py
pywebio_battery/__version__.py
pywebio_battery/file_picker.py
pywebio_battery/interaction.py
pywebio_battery/web.py
pywebio_battery.egg-info/PKG-INFO
pywebio_battery.egg-info/SOURCES.txt
pywebio_battery.egg-info/dependency_links.txt
pywebio_battery.egg-info/requires.txt
pywebio_battery.egg-info/top_level.txt