Metadata-Version: 2.1
Name: pywebio-battery
Version: 0.6.0
Summary: Utilities that help write PyWebIO apps quickly and easily.
Home-page: https://pywebio.readthedocs.io/en/latest/battery.html
Author: WeiminWang
Author-email: wang0.618@qq.com
License: MIT
Project-URL: Documentation, https://pywebio.readthedocs.io/en/latest/battery.html
Project-URL: Source, https://github.com/wang0618/pywebio-battery
Platform: UNKNOWN
Classifier: Programming Language :: Python :: 3
Classifier: Programming Language :: Python :: 3.5
Classifier: Programming Language :: Python :: 3.6
Classifier: Programming Language :: Python :: 3.7
Classifier: Programming Language :: Python :: 3.8
Requires-Python: >=3.5.2
License-File: LICENSE
